{
    "name": "AL Best Practice Ruleset",
    "description": "Recommended rules for Per-Tenant Extension development",
    "rules": [
      {
        "id": "AA0001", "action": "Warning"
      },
      {
        "id": "AA0002", "action": "Warning"
      },
      {
        "id": "AA0003", "action": "Warning"
      },
      {
        "id": "AA0004", "action": "Warning"
      },
      {
        "id": "AA0005", "action": "Warning"
      },
      {
        "id": "AA0008", "action": "Warning"
      },
      {
        "id": "AA0016", "action": "Warning"
      },
      {
        "id": "AA0137", "action": "Warning"
      },
      {
        "id": "AA0139", "action": "Warning"
      },
      {
        "id": "AA0135", "action": "Warning" 
      },
      {
        "id": "AA0134", "action": "Warning"  
      },
      {
        "id": "AA0136", "action": "Warning"
      }
      
    ]
  }  